[
{"name": "Bit Earner", "link": "/en/advertiserDetail?advertiserNo=s6cf8a81e12183203bc374b3b354f5074", "completed": "87.96% completion", "order_count": "285  orders", "price": "0.73", "currency": "GBP", "available": "47,133.42 USDT", "low_limit": "5.00", "high_limit": "500.00", "payment": "Transferwise", "crypto": "USDT", "side": "sell", "date": "2021-11-02 18:43:35"},
{"name": "Crypto Queen", "link": "/en/advertiserDetail?advertiserNo=s28adb3c59cde39a783017a0eba194e4a", "completed": "98.62% completion", "order_count": "214  orders", "price": "0.73", "currency": "GBP", "available": "239.51 USDT", "low_limit": "25.00", "high_limit": "174.84", "payment": "Transferwise", "crypto": "USDT", "side": "sell", "date": "2021-11-02 18:43:35"},
{"name": "Bit_Earner", "link": "/en/advertiserDetail?advertiserNo=s63c09288618d3b7a86f94ed58117c1f1", "completed": "90.36% completion", "order_count": "1022  orders", "price": "0.73", "currency": "GBP", "available": "47,916.45 USDT", "low_limit": "5.00", "high_limit": "700.00", "payment": "Transferwise", "crypto": "USDT", "side": "sell", "date": "2021-11-02 18:43:35"},
{"name": "Elys❤️", "link": "/en/advertiserDetail?advertiserNo=se3fe26c061db3f1b9fb18114de28ab35", "completed": "93.95% completion", "order_count": "295  orders", "price": "0.73", "currency": "GBP", "available": "155.00 USDT", "low_limit": "10.00", "high_limit": "113.15", "payment": "Transferwise", "crypto": "USDT", "side": "sell", "date": "2021-11-02 18:43:35"},
{"name": "Karam Elmahdi", "link": "/en/advertiserDetail?advertiserNo=s7bd0e9d72fcf3d9eb251b81248434ac6", "completed": "94.23% completion", "order_count": "294  orders", "price": "0.73", "currency": "GBP", "available": "1,024.79 USDT", "low_limit": "50.00", "high_limit": "748.09", "payment": "Transferwise", "crypto": "USDT", "side": "sell", "date": "2021-11-02 18:43:35"},
{"name": "MoneyMaker", "link": "/en/advertiserDetail?advertiserNo=s751a99cd8d4135af8a90d68cb83b25ff", "completed": "97.87% completion", "order_count": "92  orders", "price": "0.73", "currency": "GBP", "available": "900.00 USDT", "low_limit": "10.00", "high_limit": "657.00", "payment": "Transferwise", "crypto": "USDT", "side": "sell", "date": "2021-11-02 18:43:35"},
{"name": "Rajab Exchange ", "link": "/en/advertiserDetail?advertiserNo=s77f33ff35ea7302ea1ad360d561c526f", "completed": "94.87% completion", "order_count": "74  orders", "price": "0.73", "currency": "GBP", "available": "215.00 USDT", "low_limit": "1.00", "high_limit": "155.00", "payment": "Transferwise", "crypto": "USDT", "side": "sell", "date": "2021-11-02 18:43:35"},
{"name": "mrrana", "link": "/en/advertiserDetail?advertiserNo=se4f3133f170c3ef9a7ac460dfd943a82", "completed": "92.22% completion", "order_count": "237  orders", "price": "0.73", "currency": "GBP", "available": "131.13 USDT", "low_limit": "1.00", "high_limit": "95.72", "payment": "Transferwise", "crypto": "USDT", "side": "sell", "date": "2021-11-02 18:43:35"},
{"name": "waleed Yousaf ", "link": "/en/advertiserDetail?advertiserNo=s7c642ad2f099376e9c78bc18c3acd0e3", "completed": "90.47% completion", "order_count": "484  orders", "price": "0.73", "currency": "GBP", "available": "202.06 USDT", "low_limit": "20.00", "high_limit": "147.50", "payment": "Transferwise", "crypto": "USDT", "side": "sell", "date": "2021-11-02 18:43:35"},
{"name": "JW83", "link": "/en/advertiserDetail?advertiserNo=sa4c00a84a6a334068b525e733affb498", "completed": "93.33% completion", "order_count": "56  orders", "price": "0.73", "currency": "GBP", "available": "10,115.19 USDT", "low_limit": "10.00", "high_limit": "5,000.00", "payment": "Revolut", "crypto": "USDT", "side": "sell", "date": "2021-11-02 18:43:35"}
]